electropython/__init__.py
electropython/main.py
electropython-1.0.dist-info/LICENSE.txt
electropython-1.0.dist-info/METADATA
electropython-1.0.dist-info/WHEEL
electropython-1.0.dist-info/top_level.txt
electropython-1.0.dist-info/RECORD
