Metadata-Version: 2.1
Name: electropython
Version: 1.0
Summary: A utility Python library
Author: BlueJFlamesLab
License: MIT
Classifier: Programming Language :: Python :: 3
Classifier: License :: OSI Approved :: MIT License
Classifier: Operating System :: OS Independent
Requires-Python: >=3.0
License-File: LICENSE.txt
